{
  "gitSyncId": "68b6eff59289a93060f5089f_041df47c-8bf6-4114-9581-72c4c1342811",
  "id": "New Sale_sale_items_insert",
  "pluginId": "postgres-plugin",
  "pluginType": "DB",
  "unpublishedAction": {
    "actionConfiguration": {
      "body": "INSERT INTO bj.sale_items (sale_id, inventory_id, offered_price)\nVALUES ({{this.params.sale_id}}, {{this.params.inventory_id}}, {{this.params.offered_price}})",
      "encodeParamsToggle": true,
      "paginationType": "NONE",
      "pluginSpecifiedTemplates": [
        {
          "value": true
        }
      ],
      "timeoutInMillisecond": 10000
    },
    "confirmBeforeExecute": false,
    "datasource": {
      "id": "BJ Neon",
      "isAutoGenerated": false,
      "name": "BJ Neon",
      "pluginId": "postgres-plugin"
    },
    "dynamicBindingPathList": [
      {
        "key": "body"
      }
    ],
    "name": "sale_items_insert",
    "pageId": "New Sale",
    "runBehaviour": "MANUAL",
    "userSetOnLoad": false
  }
}