{
  "gitSyncId": "68b6eff59289a93060f5089f_728e5019-f5fc-43eb-8701-f2f7c9ff48e2",
  "id": "Inventory_insert_new_inventory",
  "pluginId": "postgres-plugin",
  "pluginType": "DB",
  "unpublishedAction": {
    "actionConfiguration": {
      "body": "insert INTO bj.inventory(branch_id, code, size, metal_weight, diamond_weight)\nVALUES ('a758efa5-39c1-4a52-a27b-55b8cc979487', {{code_select_add.selectedOptionValue}}, {{Input_1.text}}, {{Input2.text}}, {{Input3.text}});",
      "encodeParamsToggle": true,
      "paginationType": "NONE",
      "pluginSpecifiedTemplates": [
        {
          "value": true
        }
      ],
      "timeoutInMillisecond": 30000
    },
    "confirmBeforeExecute": false,
    "datasource": {
      "id": "BJ Neon",
      "isAutoGenerated": false,
      "name": "BJ Neon",
      "pluginId": "postgres-plugin"
    },
    "dynamicBindingPathList": [
      {
        "key": "body"
      }
    ],
    "name": "insert_new_inventory",
    "pageId": "Inventory",
    "runBehaviour": "MANUAL",
    "userSetOnLoad": false
  }
}