{
  "animateLoading": true,
  "borderRadius": "{{appsmith.theme.borderRadius.appBorderRadius}}",
  "bottomRow": 17,
  "boxShadow": "none",
  "buttonColor": "#ef4444",
  "buttonStyle": "PRIMARY_BUTTON",
  "buttonVariant": "PRIMARY",
  "disabledWhenInvalid": false,
  "dynamicBindingPathList": [
    {
      "key": "borderRadius"
    },
    {
      "key": "isDisabled"
    }
  ],
  "dynamicPropertyPathList": [
    {
      "key": "isDisabled"
    }
  ],
  "dynamicTriggerPathList": [
    {
      "key": "onClick"
    }
  ],
  "isDefaultClickDisabled": true,
  "isDisabled": "{{!(Input2.text == '3810000')}}",
  "isLoading": false,
  "isVisible": true,
  "key": "v0cuo1pj0i",
  "leftColumn": 2,
  "minWidth": 120,
  "mobileBottomRow": 22,
  "mobileLeftColumn": 47,
  "mobileRightColumn": 63,
  "mobileTopRow": 18,
  "needsErrorInfo": false,
  "onClick": "{{showModal(Modal2.name);}}",
  "parentId": "4j7da7zn8e",
  "placement": "CENTER",
  "recaptchaType": "V3",
  "renderMode": "CANVAS",
  "resetFormOnClick": false,
  "responsiveBehavior": "hug",
  "rightColumn": 18,
  "text": "Exit",
  "topRow": 13,
  "type": "BUTTON_WIDGET",
  "version": 1,
  "widgetId": "qeitrtp1nv",
  "widgetName": "Button7"
}