{
  "animateLoading": true,
  "borderRadius": "{{appsmith.theme.borderRadius.appBorderRadius}}",
  "bottomRow": 48,
  "boxShadow": "none",
  "defaultImage": "",
  "dynamicBindingPathList": [
    {
      "key": "borderRadius"
    },
    {
      "key": "image"
    }
  ],
  "dynamicTriggerPathList": [],
  "enableDownload": false,
  "enableRotation": false,
  "flexVerticalAlignment": "start",
  "image": "{{FilePicker1.files[1].data}}",
  "imageShape": "RECTANGLE",
  "isLoading": false,
  "isVisible": true,
  "key": "ikmbl5ark1",
  "leftColumn": 11,
  "maxZoomLevel": 1,
  "mobileBottomRow": 47,
  "mobileLeftColumn": 1,
  "mobileRightColumn": 13,
  "mobileTopRow": 35,
  "needsErrorInfo": false,
  "objectFit": "cover",
  "originalBottomRow": 56,
  "originalTopRow": 47,
  "parentColumnSpace": 11,
  "parentId": "gs9yfm8fdc",
  "parentRowSpace": 10,
  "renderMode": "CANVAS",
  "rightColumn": 20,
  "topRow": 39,
  "type": "IMAGE_WIDGET",
  "version": 1,
  "widgetId": "wbpj4h9w1o",
  "widgetName": "Image3Copy2"
}